shellsmith/__init__.py
shellsmith/__main__.py
shellsmith/api.py
shellsmith/clients.py
shellsmith/config.py
shellsmith/extract.py
shellsmith/neo4j.py
shellsmith/services.py
shellsmith/types.py
shellsmith/upload.py
shellsmith/utils.py
shellsmith-0.5.0.dist-info/METADATA
shellsmith-0.5.0.dist-info/WHEEL
shellsmith-0.5.0.dist-info/licenses/LICENSE
shellsmith-0.5.0.dist-info/RECORD
