Metadata-Version: 2.4
Name: shellsmith
Version: 0.5.0
Summary: A Python SDK for Eclipse BaSyx to manage Asset Administration Shells (AAS)
Project-URL: Homepage, https://github.com/SmartFactory-KL/shellsmith
Project-URL: Issues, https://github.com/SmartFactory-KL/shellsmith/issues
Project-URL: Documentation, https://shellsmith.pages.dev
Author-email: Peter Stein <peter.stein@dfki.de>
License: MIT License
License-File: LICENSE
Keywords: aas,asset-administration-shell,basyx,digital-twin,eclipse-basyx,i40,industry40,python,rest-client
Classifier: Environment :: Console
Classifier: Intended Audience :: Developers
Classifier: License :: OSI Approved :: MIT License
Classifier: Operating System :: OS Independent
Classifier: Programming Language :: Python :: 3
Classifier: Programming Language :: Python :: 3.10
Classifier: Programming Language :: Python :: 3.11
Classifier: Programming Language :: Python :: 3.12
Classifier: Programming Language :: Python :: 3.13
Classifier: Topic :: Software Development :: Libraries
Classifier: Topic :: Software Development :: Libraries :: Python Modules
Requires-Python: >=3.10
Requires-Dist: httpx
Requires-Dist: pydantic-settings
Requires-Dist: pyyaml
Provides-Extra: cli
Requires-Dist: aas-cli; extra == 'cli'
Provides-Extra: docs
Requires-Dist: mkdocs; extra == 'docs'
Requires-Dist: mkdocs-material; extra == 'docs'
Requires-Dist: termynal; extra == 'docs'
Provides-Extra: mcp
Requires-Dist: aas-mcp; extra == 'mcp'
Provides-Extra: neo4j
Requires-Dist: neo4j; extra == 'neo4j'
Provides-Extra: test
Requires-Dist: mypy; extra == 'test'
Requires-Dist: pytest; extra == 'test'
Requires-Dist: pytest-asyncio; extra == 'test'
Requires-Dist: pytest-cov; extra == 'test'
Requires-Dist: pytest-dotenv; extra == 'test'
Requires-Dist: ruff; extra == 'test'
Requires-Dist: types-pyyaml; extra == 'test'
Requires-Dist: types-requests; extra == 'test'
